{
    "levelIndex": 26,
    "targetScore": 252,
    "moveLimit": 43,
    "levelType": "AUTO_GEN",
    "groups": [
        {
            "groupName": "Group_26",
            "shapeType": "",
            "positions": [
                {
                    "x": -3.190722942352295,
                    "y": 0.5,
                    "z": -2.9636192321777345
                },
                {
                    "x": -0.9997804760932922,
                    "y": 0.5,
                    "z": -0.15540972352027894
                },
                {
                    "x": 2.3649771213531496,
                    "y": 0.5,
                    "z": 3.089160680770874
                },
                {
                    "x": -5.093738555908203,
                    "y": 0.5,
                    "z": 1.3103032112121583
                },
                {
                    "x": -2.4061787128448488,
                    "y": 0.5,
                    "z": -3.1522340774536135
                },
                {
                    "x": -4.115926742553711,
                    "y": 0.5,
                    "z": -0.7863222360610962
                },
                {
                    "x": -4.646483898162842,
                    "y": 0.5,
                    "z": 2.359719753265381
                },
                {
                    "x": -1.2848962545394898,
                    "y": 0.5,
                    "z": 4.9492645263671879
                },
                {
                    "x": 3.228055477142334,
                    "y": 0.5,
                    "z": -2.872462511062622
                },
                {
                    "x": 1.9119913578033448,
                    "y": 0.5,
                    "z": 0.07793119549751282
                },
                {
                    "x": -2.15556001663208,
                    "y": 0.5,
                    "z": 0.22175592184066773
                },
                {
                    "x": 2.866485357284546,
                    "y": 0.5,
                    "z": 4.659213542938232
                },
                {
                    "x": -1.2100354433059693,
                    "y": 0.5,
                    "z": -5.195843696594238
                },
                {
                    "x": 2.749582290649414,
                    "y": 0.5,
                    "z": 1.1650196313858033
                },
                {
                    "x": 1.3592321872711182,
                    "y": 0.5,
                    "z": -5.363086700439453
                },
                {
                    "x": 3.261549234390259,
                    "y": 0.5,
                    "z": 2.1534345149993898
                },
                {
                    "x": -2.475776433944702,
                    "y": 0.5,
                    "z": 1.7074698209762574
                },
                {
                    "x": -3.744189500808716,
                    "y": 0.5,
                    "z": -3.0684032440185549
                },
                {
                    "x": 1.9600462913513184,
                    "y": 0.5,
                    "z": -4.414487838745117
                },
                {
                    "x": 4.26663064956665,
                    "y": 0.5,
                    "z": 2.6278128623962404
                },
                {
                    "x": -4.470028400421143,
                    "y": 0.5,
                    "z": 3.1421897411346437
                },
                {
                    "x": 4.171285629272461,
                    "y": 0.5,
                    "z": 3.0799522399902345
                },
                {
                    "x": 3.1397900581359865,
                    "y": 0.5,
                    "z": 3.3173484802246095
                },
                {
                    "x": -2.4676456451416017,
                    "y": 0.5,
                    "z": 1.322746992111206
                },
                {
                    "x": -2.106858253479004,
                    "y": 0.5,
                    "z": -4.151978015899658
                },
                {
                    "x": 3.17130446434021,
                    "y": 0.5,
                    "z": 2.0958874225616457
                },
                {
                    "x": -0.07589957118034363,
                    "y": 0.5,
                    "z": 0.6551154255867004
                },
                {
                    "x": -1.8009369373321534,
                    "y": 0.5,
                    "z": 1.7003751993179322
                },
                {
                    "x": -5.444088935852051,
                    "y": 0.5,
                    "z": -0.6535897850990295
                },
                {
                    "x": 2.1490478515625,
                    "y": 0.5,
                    "z": -2.08833909034729
                },
                {
                    "x": 1.1978415250778199,
                    "y": 0.5,
                    "z": -1.63140869140625
                },
                {
                    "x": -2.357171058654785,
                    "y": 0.5,
                    "z": -1.395073413848877
                },
                {
                    "x": -3.215837001800537,
                    "y": 0.5,
                    "z": 2.7737622261047365
                },
                {
                    "x": 1.57387113571167,
                    "y": 0.5,
                    "z": 1.7070372104644776
                },
                {
                    "x": -4.758465766906738,
                    "y": 0.5,
                    "z": -2.0883939266204836
                },
                {
                    "x": -1.6990602016448975,
                    "y": 0.5,
                    "z": 2.6656296253204347
                }
            ]
        }
    ]
}